{
  "id": "hammond-1590x",
  "manufacturer": "Hammond",
  "model": "1590X",
  "unit": "mm",
  "source": "https://www.hammfg.com/files/parts/pdf/1590X.pdf",
  "faces": {
    "A": { "width": 121.20, "height": 145.20 },
    "B": { "shape": "trapezoid", "top_width": 118.46, "bottom_width": 121.20, "height": 52.30 },
    "C": { "shape": "trapezoid", "top_width": 142.46, "bottom_width": 145.20, "height": 52.30 },
    "D": { "shape": "trapezoid", "top_width": 118.46, "bottom_width": 121.20, "height": 52.30 },
    "E": { "shape": "trapezoid", "top_width": 142.46, "bottom_width": 145.20, "height": 52.30 }
  }
}
